{
	"credit": "Made with Blockbench",
	"textures": {
		"1": "vs_clockwork:block/heatpipe_connection_very_hot",
		"particle": "vs_clockwork:block/heatpipe_core"
	},
	"elements": [
		{
			"from": [5, 5, 0],
			"to": [11, 11, 5],
			"rotation": {"angle": 0, "axis": "y", "origin": [8, 8, 8]},
			"faces": {
				"east": {"uv": [0, 10, 5, 16], "texture": "#1"},
				"west": {"uv": [5, 10, 0, 16], "texture": "#1"},
				"up": {"uv": [10, 11, 16, 16], "texture": "#1"},
				"down": {"uv": [10, 16, 16, 11], "texture": "#1"}
			}
		},
		{
			"from": [4.925, 4.925, 0],
			"to": [11.075, 11.075, 5],
			"rotation": {"angle": 0, "axis": "y", "origin": [8, 8, 8]},
			"faces": {
				"east": {"uv": [5, 10, 10, 16], "texture": "#1"},
				"west": {"uv": [10, 10, 5, 16], "texture": "#1"},
				"up": {"uv": [10, 6, 16, 11], "texture": "#1"},
				"down": {"uv": [10, 11, 16, 6], "texture": "#1"}
			}
		}
	],
	"display": {
		"thirdperson_righthand": {
			"rotation": [75, 45, 0],
			"translation": [0, 2.5, 0],
			"scale": [0.375, 0.375, 0.375]
		},
		"thirdperson_lefthand": {
			"rotation": [75, 45, 0],
			"translation": [0, 2.5, 0],
			"scale": [0.375, 0.375, 0.375]
		},
		"firstperson_righthand": {
			"rotation": [0, 45, 0],
			"scale": [0.4, 0.4, 0.4]
		},
		"firstperson_lefthand": {
			"rotation": [0, 225, 0],
			"scale": [0.4, 0.4, 0.4]
		},
		"ground": {
			"translation": [0, 3, 0],
			"scale": [0.25, 0.25, 0.25]
		},
		"gui": {
			"rotation": [30, 225, 0],
			"scale": [0.625, 0.625, 0.625]
		},
		"fixed": {
			"scale": [0.5, 0.5, 0.5]
		}
	},
	"groups": [
		{
			"name": "connection",
			"origin": [8, 8, 8],
			"color": 0,
			"children": [
				{
					"name": "north",
					"origin": [8, 8, 8],
					"color": 0,
					"children": [0, 1]
				}
			]
		}
	]
}